[
  {
    "tieneQueso": false,
    "idProducto": 1,
    "nombre": "Pan francés",
    "stock": 150,
    "precio": 800.0,
    "costo": 500.0,
    "tipo": "Pan"
  },
  {
    "tieneChispas": false,
    "idProducto": 2,
    "nombre": "Galleta de avena",
    "stock": 60,
    "precio": 1500.0,
    "costo": 900.0,
    "tipo": "Galleta"
  },
  {
    "tieneQueso": false,
    "idProducto": 3,
    "nombre": "Pan de queso",
    "stock": 90,
    "precio": 1200.0,
    "costo": 700.0,
    "tipo": "Pan"
  },
  {
    "tieneChispas": false,
    "idProducto": 4,
    "nombre": "Galleta de chocolate",
    "stock": 30,
    "precio": 5000.0,
    "costo": 3000.0,
    "tipo": "Galleta"
  },
  {
    "tieneQueso": false,
    "idProducto": 5,
    "nombre": "Pan integral",
    "stock": 45,
    "precio": 900.0,
    "costo": 550.0,
    "tipo": "Pan"
  },
  {
    "tieneChispas": false,
    "idProducto": 6,
    "nombre": "Galleta de mantequilla",
    "stock": 80,
    "precio": 1200.0,
    "costo": 700.0,
    "tipo": "Galleta"
  },
  {
    "tieneQueso": false,
    "idProducto": 7,
    "nombre": "Pan de ajo",
    "stock": 60,
    "precio": 1000.0,
    "costo": 600.0,
    "tipo": "Pan"
  },
  {
    "tieneChispas": false,
    "idProducto": 8,
    "nombre": "Galleta de vainilla",
    "stock": 70,
    "precio": 1300.0,
    "costo": 800.0,
    "tipo": "Galleta"
  },
  {
    "tieneQueso": false,
    "idProducto": 9,
    "nombre": "Pan de centeno",
    "stock": 40,
    "precio": 1100.0,
    "costo": 650.0,
    "tipo": "Pan"
  },
  {
    "tieneChispas": false,
    "idProducto": 10,
    "nombre": "Galleta de almendra",
    "stock": 55,
    "precio": 1800.0,
    "costo": 1100.0,
    "tipo": "Galleta"
  },
  {
    "tieneQueso": false,
    "idProducto": 11,
    "nombre": "Pan de maíz",
    "stock": 35,
    "precio": 950.0,
    "costo": 570.0,
    "tipo": "Pan"
  },
  {
    "tieneChispas": false,
    "idProducto": 12,
    "nombre": "Galleta de jengibre",
    "stock": 45,
    "precio": 1600.0,
    "costo": 950.0,
    "tipo": "Galleta"
  },
  {
    "tieneQueso": false,
    "idProducto": 13,
    "nombre": "Pan de leche",
    "stock": 65,
    "precio": 880.0,
    "costo": 520.0,
    "tipo": "Pan"
  },
  {
    "tieneChispas": false,
    "idProducto": 14,
    "nombre": "Galleta de coco",
    "stock": 50,
    "precio": 1700.0,
    "costo": 1000.0,
    "tipo": "Galleta"
  },
  {
    "tieneQueso": false,
    "idProducto": 15,
    "nombre": "Pan de aceitunas",
    "stock": 30,
    "precio": 1300.0,
    "costo": 780.0,
    "tipo": "Pan"
  },
  {
    "tieneChispas": false,
    "idProducto": 16,
    "nombre": "Galleta de limón",
    "stock": 40,
    "precio": 1400.0,
    "costo": 850.0,
    "tipo": "Galleta"
  },
  {
    "tieneQueso": false,
    "idProducto": 17,
    "nombre": "Pan de calabaza",
    "stock": 25,
    "precio": 1200.0,
    "costo": 720.0,
    "tipo": "Pan"
  },
  {
    "tieneChispas": false,
    "idProducto": 18,
    "nombre": "Galleta de canela",
    "stock": 60,
    "precio": 1450.0,
    "costo": 870.0,
    "tipo": "Galleta"
  },
  {
    "tieneQueso": false,
    "idProducto": 19,
    "nombre": "Pan de queso con jalapeño",
    "stock": 35,
    "precio": 1500.0,
    "costo": 900.0,
    "tipo": "Pan"
  },
  {
    "tieneChispas": true,
    "idProducto": 20,
    "nombre": "Galleta de avena y pasas",
    "stock": 45,
    "precio": 1650.0,
    "costo": 990.0,
    "tipo": "Galleta"
  }
]